encoding_repair
