Metadata-Version: 1.0
Name: encoding-repair
Version: 0.7dev
Summary: Helpers to repair encodings (especially umlauts)
Home-page: https://bitbucket.org/niels_mfo/encoding_repair
Author: Niels Ranosch
Author-email: ranosch@mfo.de
License: MIT
Keywords: encoding utf-8 latin1 character magic umlaut special unicode
Platform: UNKNOWN
